{
  "action": "run",
  "variant": "run",
  "frame_index": 50,
  "phase": "drive",
  "keypoints": {
    "nose": [
      0.545,
      0.2
    ],
    "neck": [
      0.545,
      0.31
    ],
    "right_shoulder": [
      0.625,
      0.35
    ],
    "right_elbow": [
      0.6880828027974359,
      0.48
    ],
    "right_wrist": [
      0.7569324844758976,
      0.5807668788810256
    ],
    "left_shoulder": [
      0.46499999999999997,
      0.35
    ],
    "left_elbow": [
      0.31191719720256406,
      0.48
    ],
    "left_wrist": [
      0.2430675155241025,
      0.6192331211189743
    ],
    "right_hip": [
      0.5950000000000001,
      0.57
    ],
    "right_knee": [
      0.5423006366430768,
      0.74
    ],
    "right_ankle": [
      0.533834394405128,
      0.89
    ],
    "left_hip": [
      0.495,
      0.57
    ],
    "left_knee": [
      0.4576993633569232,
      0.7183627387411539
    ],
    "left_ankle": [
      0.4661656055948719,
      0.8419171972025641
    ]
  },
  "notes": "run drive"
}
