{
  "action": "run",
  "variant": "run",
  "frame_index": 86,
  "phase": "flight",
  "keypoints": {
    "nose": [
      0.545,
      0.18822244964470414
    ],
    "neck": [
      0.545,
      0.2982224496447041
    ],
    "right_shoulder": [
      0.625,
      0.3382224496447041
    ],
    "right_elbow": [
      0.5414687117760503,
      0.48
    ],
    "right_wrist": [
      0.5223499388416805,
      0.6394125152895799
    ],
    "left_shoulder": [
      0.46499999999999997,
      0.3382224496447041
    ],
    "left_elbow": [
      0.45853128822394973,
      0.48
    ],
    "left_wrist": [
      0.4776500611583196,
      0.5605874847104201
    ],
    "right_hip": [
      0.5950000000000001,
      0.558222449644704
    ],
    "right_knee": [
      0.7182375458687397,
      0.6956609202992226
    ],
    "right_ankle": [
      0.8270625764478995,
      0.7796911614207545
    ],
    "left_hip": [
      0.495,
      0.558222449644704
    ],
    "left_knee": [
      0.28176245413126033,
      0.74
    ],
    "left_ankle": [
      0.1729374235521005,
      0.8782224496447041
    ]
  },
  "notes": "run flight"
}
