{
  "action": "run",
  "variant": "run",
  "frame_index": 46,
  "phase": "drive",
  "keypoints": {
    "nose": [
      0.545,
      0.2
    ],
    "neck": [
      0.545,
      0.31
    ],
    "right_shoulder": [
      0.625,
      0.35
    ],
    "right_elbow": [
      0.7053953365296969,
      0.48
    ],
    "right_wrist": [
      0.784632538447515,
      0.5738418653881212
    ],
    "left_shoulder": [
      0.46499999999999997,
      0.35
    ],
    "left_elbow": [
      0.2946046634703032,
      0.48
    ],
    "left_wrist": [
      0.2153674615524851,
      0.6261581346118787
    ],
    "right_hip": [
      0.5950000000000001,
      0.57
    ],
    "right_knee": [
      0.5215255961643638,
      0.74
    ],
    "right_ankle": [
      0.49920932694060627,
      0.89
    ],
    "left_hip": [
      0.495,
      0.57
    ],
    "left_knee": [
      0.4784744038356362,
      0.7105720985616364
    ],
    "left_ankle": [
      0.5007906730593936,
      0.8246046634703031
    ]
  },
  "notes": "run drive"
}
