{
  "action": "hit",
  "variant": "light",
  "frame_index": 113,
  "phase": "recover",
  "keypoints": {
    "nose": [
      0.5076830732292917,
      0.2
    ],
    "neck": [
      0.5048019207683073,
      0.31
    ],
    "right_shoulder": [
      0.5848019207683073,
      0.35
    ],
    "right_elbow": [
      0.6448019207683073,
      0.48
    ],
    "right_wrist": [
      0.6790396158463385,
      0.6
    ],
    "left_shoulder": [
      0.4248019207683073,
      0.35
    ],
    "left_elbow": [
      0.3648019207683073,
      0.48
    ],
    "left_wrist": [
      0.3180792316926771,
      0.6
    ],
    "right_hip": [
      0.5548019207683074,
      0.57
    ],
    "right_knee": [
      0.6048019207683073,
      0.74
    ],
    "right_ankle": [
      0.6348019207683073,
      0.89
    ],
    "left_hip": [
      0.45480192076830733,
      0.57
    ],
    "left_knee": [
      0.40480192076830734,
      0.74
    ],
    "left_ankle": [
      0.3748019207683073,
      0.89
    ]
  },
  "notes": "hit_light recover"
}
