{
  "action": "walk",
  "variant": "walk",
  "frame_index": 101,
  "phase": "up",
  "keypoints": {
    "nose": [
      0.5,
      0.2
    ],
    "neck": [
      0.5,
      0.31
    ],
    "right_shoulder": [
      0.58,
      0.35
    ],
    "right_elbow": [
      0.64,
      0.48
    ],
    "right_wrist": [
      0.6149082543272673,
      0.6
    ],
    "left_shoulder": [
      0.42,
      0.35
    ],
    "left_elbow": [
      0.36,
      0.48
    ],
    "left_wrist": [
      0.38509174567273285,
      0.6
    ],
    "right_hip": [
      0.55,
      0.57
    ],
    "right_knee": [
      0.6569552774636412,
      0.74
    ],
    "right_ankle": [
      0.7276376185090992,
      0.849317658954542
    ],
    "left_hip": [
      0.45,
      0.57
    ],
    "left_knee": [
      0.3430447225363588,
      0.74
    ],
    "left_ankle": [
      0.27236238149090075,
      0.89
    ]
  },
  "notes": "walk up"
}
