{
  "weapon": "sword",
  "frame_index": 2,
  "phase": "ready",
  "anchors": {
    "main_hand": [
      0.5094863239912563,
      0.5197771810188208
    ],
    "blade_tip": [
      0.3144703356319005,
      0.24126548596056357
    ],
    "pommel": [
      0.543900910172319,
      0.5689263036761603
    ]
  },
  "lines": [
    {
      "start": "pommel",
      "end": "blade_tip",
      "width": 7,
      "color": [
        0,
        240,
        255
      ]
    }
  ],
  "arcs": []
}
